{
    "info": "None",
    "start_epoch": 1,
    "epochs": 50,
    "batch_size": 100,
    "optimizer": "AdamW",
    "lr": 0.001,
    "step_lr": false,
    "step_size": 10,
    "gamma": 0.5,
    "workers": 4,
    "dataset_splits": "[8,2]",
    "shuffle_dataset": true,
    "random_seed": 18000,
    "device": "cuda",
    "enable_logging": true,
    "enable_saving": true,
    "logging_path": "logging",
    "saving_path": "saving",
    "save_num_best": 2,
    "save_mode": "best",
    "save_model_name": "model",
    "save_every_epochs": 10,
    "save_last": false,
    "primary_score": "val_score",
    "higher_better": true,
    "early_stop": true,
    "early_stop_num": 10,
    "folder_id": "bert",
    "resume_path": null,
    "debug": false,
    "config_file": null,
    "h_size": 256,
    "vocab_file": "data/vocab.pkl",
    "dropout": 0,
    "num_label": 17,
    "data_file": "data/rd1_train.csv",
    "label_file": "data/rd1_train_label.csv",
    "desc_max_len": 100,
    "n_fold": 20,
    "n_layer": 8,
    "n_head": 8,
    "test_file": "data/rd1_testA.csv",
    "output_path": "pred",
    "seq_mask_ratio": 0.15,
    "seq_pad_meth": "post",
    "pretrain_model_file": "saving/=2021_04_07_16_27_36_bert_pretrain=/last/model.pth",
    "model_name": "bert",
    "val_score_limit": 0.974
}